scrapingtype/__init__.py
scrapingtype-0.0.3.dist-info/METADATA
scrapingtype-0.0.3.dist-info/WHEEL
scrapingtype-0.0.3.dist-info/top_level.txt
scrapingtype-0.0.3.dist-info/RECORD
