Metadata-Version: 2.1
Name: scrapingtype
Version: 0.0.3
Summary: A basic package for helping Sloths team to find a current scraping type for a site
Home-page: UNKNOWN
Author: VladimirSavchenko
Author-email: savchenko.vldmr@gmail.com
License: UNKNOWN
Keywords: Sloths,360,scraping
Platform: UNKNOWN
Classifier: Development Status :: 1 - Planning
Classifier: Intended Audience :: Developers
Classifier: Programming Language :: Python :: 3
Classifier: Operating System :: Unix
Classifier: Operating System :: MacOS :: MacOS X
Classifier: Operating System :: Microsoft :: Windows
Requires-Dist: python-consul
